nppc/__init__.py
nppc/cli.py
nppc/nppc.py
nppc-0.1.0.dist-info/DESCRIPTION.rst
nppc-0.1.0.dist-info/METADATA
nppc-0.1.0.dist-info/RECORD
nppc-0.1.0.dist-info/WHEEL
nppc-0.1.0.dist-info/entry_points.txt
nppc-0.1.0.dist-info/metadata.json
nppc-0.1.0.dist-info/top_level.txt
