Metadata-Version: 2.0
Name: nppc
Version: 0.1.0
Summary: NPPC, Nagios Plug-in Process Controller, is a set of scripts and configuration files that let you periodically runs Nagios_ Plug-in parallel using systemd_ and systemd.timer_. Results can be posted via HTTPS to a NSCAweb_ server.
Home-page: https://github.com/maartenq/nppc
Author: Maarten
Author-email: ikmaarten@gmail.com
License: ISC license
Keywords: nppc
Platform: UNKNOWN
Classifier: Development Status :: 2 - Pre-Alpha
Classifier: Intended Audience :: Developers
Classifier: License :: OSI Approved :: ISC License (ISCL)
Classifier: Natural Language :: English
Classifier: Programming Language :: Python :: 2
Classifier: Programming Language :: Python :: 2.7
Classifier: Programming Language :: Python :: 3
Classifier: Programming Language :: Python :: 3.4
Classifier: Programming Language :: Python :: 3.5
Classifier: Programming Language :: Python :: 3.6
Requires-Dist: Click (>=6.0)
